<?xml version="1.0" encoding="utf-8"?>
<Persons>
  <Customers>
    <Customer>
      <Id>1</Id>
      <State>Aktiv</State>
      <Salutation>Herr</Salutation>
      <Title>Dr</Title>
      <FirstName>Max</FirstName>
      <LastName>Halter</LastName>
      <Sex>männlich</Sex>
      <Function>Einkaufsleiter</Function>
      <CompanyName>Test AG</CompanyName>
      <CustomerType>A</CustomerType>
      <Address>
        <Street>Oberdorfstrasse</Street>
        <Number>6</Number>
        <City>Luzern</City>
        <Zip>8000</Zip>
        <Country>Schweiz</Country>
      </Address>
      <ContactData>
        <Phone Type="Business">+41-12-123-1234</Phone>
        <Phone Type="Mobile">+41-12-123-2345</Phone>
        <Fax>+41-12-123-3456</Fax>
        <EMail>max.muster@admin.ch</EMail>
      </ContactData>
      <Logs></Logs>
      <MutationLogs>
        <MutationLog>Personen Id: 1; Attribut: Vorname; Wert alt: Max; Wert neu: Markus; Zeitpunkt; 06.09.2021 19:29:31</MutationLog>
        <MutationLog>Personen Id: 1; Attribut: Vorname; Wert alt: Markus; Wert neu: Max; Zeitpunkt; 06.09.2021 19:30:11</MutationLog>
        <MutationLog>Personen Id: 1; Attribut: Nachname; Wert alt: Muster; Wert neu: Halter; Zeitpunkt; 06.09.2021 19:30:11</MutationLog>
        <MutationLog>Personen Id: 1; Attribut: Hausnummer; Wert alt: 5; Wert neu: 6; Zeitpunkt; 06.09.2021 19:30:11</MutationLog>
        <MutationLog>Personen Id: 1; Attribut: Ort; Wert alt: Zürich; Wert neu: Luzern; Zeitpunkt; 06.09.2021 19:30:11</MutationLog>
        <MutationLog>Personen Id: 1; Attribut: E-Mail; Wert alt: max.muster@admin.ch; Wert neu: max.muster; Zeitpunkt; 07.09.2021 15:17:30</MutationLog>
        <MutationLog>Personen Id: 1; Attribut: Titel; Wert alt: Dr; Wert neu: ; Zeitpunkt; 07.09.2021 15:18:03</MutationLog>
        <MutationLog>Personen Id: 1; Attribut: Titel; Wert alt: ; Wert neu: Dr; Zeitpunkt; 07.09.2021 15:18:16</MutationLog>
        <MutationLog>Personen Id: 1; Attribut: Geschlecht; Wert alt: männlich; Wert neu: ; Zeitpunkt; 07.09.2021 15:43:56</MutationLog>
        <MutationLog>Personen Id: 1; Attribut: Funktion; Wert alt: Einkaufsleiter; Wert neu: ; Zeitpunkt; 07.09.2021 15:43:56</MutationLog>
        <MutationLog>Personen Id: 1; Attribut: Geschlecht; Wert alt: ; Wert neu: männlich; Zeitpunkt; 07.09.2021 15:45:10</MutationLog>
        <MutationLog>Personen Id: 1; Attribut: Funktion; Wert alt: ; Wert neu: Einkaufsleiter; Zeitpunkt; 07.09.2021 15:45:10</MutationLog>
        <MutationLog>Personen Id: 1; Attribut: E-Mail; Wert alt: max.muster; Wert neu: max.muster@admin.ch; Zeitpunkt; 07.09.2021 15:45:10</MutationLog>
      </MutationLogs>
    </Customer>
  </Customers>
  <Employees>
    <Employee>
      <Id>2</Id>
      <State>Aktiv</State>
      <Salutation>Frau</Salutation>
      <Title></Title>
      <FirstName>Anna</FirstName>
      <LastName>Bolika</LastName>
      <Sex>weiblich</Sex>
      <Function>Verkaufsleiterin</Function>
      <DateOfBirth>15.01.1980</DateOfBirth>
      <Department>Verkauf</Department>
      <InsuranceNumber>123.1234.1234.12</InsuranceNumber>
      <Citizenship>Schweiz</Citizenship>
      <EntryDate>02.01.2015</EntryDate>
      <SeparationDate></SeparationDate>
      <LevelOfEmployment>80</LevelOfEmployment>
      <Level>2</Level>
      <Address>
        <Street>Nordstrasse</Street>
        <Number>6</Number>
        <City>Goldach</City>
        <Zip>9403</Zip>
        <Country>Schweiz</Country>
      </Address>
      <ContactData>
        <Phone Type="Business">+41-23-123-1234</Phone>
        <Phone Type="Mobile">+41-32-123-1234</Phone>
        <Phone Type="Private">+41-34-123-1234</Phone>
        <EMail>anna.bolika@verkauf.ch</EMail>
      </ContactData>
    </Employee>
    <MutationLogs></MutationLogs>
  </Employees>
  <Trainees>
    <Trainee>
      <Id>3</Id>
      <State>Aktiv</State>
      <Salutation>Herr</Salutation>
      <Title></Title>
      <FirstName>Mario</FirstName>
      <LastName>Richter</LastName>
      <Sex>männlich</Sex>
      <Function>Lernender Elektroniker</Function>
      <DateOfBirth>15.01.2005</DateOfBirth>
      <Department>Produktion</Department>
      <InsuranceNumber>123.1234.1234.21</InsuranceNumber>
      <Citizenship>Schweiz</Citizenship>
      <EntryDate>02.08.2020</EntryDate>
      <SeparationDate></SeparationDate>
      <LevelOfEmployment>100</LevelOfEmployment>
      <Level>0</Level>
      <Address>
        <Street>Gäbeliweg</Street>
        <Number>6</Number>
        <City>Montlingen</City>
        <Zip>9462</Zip>
        <Country>Schweiz</Country>
      </Address>
      <ContactData>
        <Phone Type="Business">+41-23-123-1243</Phone>
        <Phone Type="Mobile">+41-32-123-1243</Phone>
        <Phone Type="Private">+41-34-123-1243</Phone>
        <EMail>mario.richter@produktion.ch</EMail>
      </ContactData>
    </Trainee>
  </Trainees>
  <MutationLogs></MutationLogs>
</Persons>